logging_fastapi/__init__.py
logging_fastapi/ctx.py
logging_fastapi/intercept_std_logging.py
logging_fastapi/logging.py
logging_fastapi/logging_fastapi.py
logging_fastapi/loki_transport.py
logging_fastapi/otel.py
logging_fastapi/request_response.py
logging_fastapi/sampler.py
logging_fastapi/storage.py
logging_fastapi/utils.py
logging_fastapi/wrap_logger.py
logging_fastapi-0.0.6.dist-info/METADATA
logging_fastapi-0.0.6.dist-info/WHEEL
logging_fastapi-0.0.6.dist-info/top_level.txt
logging_fastapi-0.0.6.dist-info/RECORD
